visual_regression_tracker/__init__.py
visual_regression_tracker/config.py
visual_regression_tracker/exceptions.py
visual_regression_tracker/playwright.py
visual_regression_tracker/types.py
visual_regression_tracker/visualRegressionTracker.py
visual_regression_tracker-4.9.0.dist-info/LICENSE
visual_regression_tracker-4.9.0.dist-info/METADATA
visual_regression_tracker-4.9.0.dist-info/WHEEL
visual_regression_tracker-4.9.0.dist-info/top_level.txt
visual_regression_tracker-4.9.0.dist-info/RECORD
