Metadata-Version: 2.1
Name: visual-regression-tracker
Version: 4.9.0
Summary: Open source, self hosted solution for visual testing and managing results of visual testing.
Home-page: https://github.com/Visual-Regression-Tracker/Visual-Regression-Tracker
Author: 
License: APACHE
Platform: UNKNOWN
Requires-Python: >=3.6
Requires-Dist: requests
Requires-Dist: dacite
Requires-Dist: dataclasses ; python_version < "3.7"
Provides-Extra: playwright
Requires-Dist: playwright ; extra == 'playwright'
